owcli/__init__.py
owcli/main.py
owcli/commands/__init__.py
owcli/commands/init/__init__.py
owcli/commands/init/main.py
owcli/template/Pipfile
owcli/template/README.md
owcli/template/setup.py
owcli/template/yourapp/__init__.py
owcli/template/yourapp/main.py
owcli/template/yourapp/commands/__init__.py
owcli/template/yourapp/commands/cmd1/__init__.py
owcli/template/yourapp/commands/cmd1/main.py
owcli/template/yourapp/commands/cmd2/__init__.py
owcli/template/yourapp/commands/cmd2/main.py
owcli/template/yourapp/commands/cmd2/subcmd1/__init__.py
owcli/template/yourapp/commands/cmd2/subcmd1/main.py
owcli/template/yourapp/commands/cmd2/subcmd2/__init__.py
owcli/template/yourapp/commands/cmd2/subcmd2/main.py
owcli/template/yourapp/commands/cmd2/subcmd3/__init__.py
owcli/template/yourapp/commands/cmd2/subcmd3/main.py
owcli/template/yourapp/commands/cmd3/__init__.py
owcli/template/yourapp/commands/cmd3/main.py
owcli-0.9.0.dist-info/METADATA
owcli-0.9.0.dist-info/WHEEL
owcli-0.9.0.dist-info/entry_points.txt
owcli-0.9.0.dist-info/licenses/LICENSE
owcli-0.9.0.dist-info/RECORD
