Metadata-Version: 2.4
Name: owcli
Version: 0.9.0
Summary: CLI framework which supports both command and subcommand.
Project-URL: homepage, https://github.com/tadashi-aikawa/owcli
Project-URL: repository, https://github.com/tadashi-aikawa/owcli/blob/master/README.md
Project-URL: documentation, https://tadashi-aikawa.github.io/owcli/
Author-email: tadashi-aikawa <syou.maman@gmail.com>
License: MIT
License-File: LICENSE
Keywords: cli framework
Classifier: Development Status :: 5 - Production/Stable
Classifier: Intended Audience :: Developers
Classifier: Topic :: Software Development :: Libraries :: Application Frameworks
Requires-Python: <4.0,>=3.9
Requires-Dist: docopt<1.0.0,>=0.6.2
Requires-Dist: owlmixin<8.0,>=7.0.1
